nnunetv2_cam/__init__.py
nnunetv2_cam/api.py
nnunetv2_cam/cam_core.py
nnunetv2_cam/cli.py
nnunetv2_cam/utils.py
nnunetv2_cam/custom_cams/__init__.py
nnunetv2_cam/custom_cams/ablation_cam_3d.py
nnunetv2_cam/custom_cams/grad_cam_plusplus_3d.py
nnunetv2_cam/custom_cams/seg_xres_cam.py
nnunetv2_cam/custom_cams/xgrad_cam_3d.py
nnunetv2_cam-0.1.6.1.dist-info/licenses/LICENSE
nnunetv2_cam-0.1.6.1.dist-info/METADATA
nnunetv2_cam-0.1.6.1.dist-info/WHEEL
nnunetv2_cam-0.1.6.1.dist-info/entry_points.txt
nnunetv2_cam-0.1.6.1.dist-info/top_level.txt
nnunetv2_cam-0.1.6.1.dist-info/RECORD
