Metadata-Version: 2.4
Name: nnunetv2-cam
Version: 0.1.6.1
Summary: Class Activation Map generation for nnUNet v2 models
Author-email: Youssef Abuzeid <youssefabuzeid0@gmail.com>
License: Apache-2.0
Project-URL: Homepage, https://github.com/Yousif-Abuzeid/nnunetv2-CAM
Project-URL: Documentation, https://github.com/Yousif-Abuzeid/nnunetv2-CAM#readme
Project-URL: Repository, https://github.com/Yousif-Abuzeid/nnunetv2-CAM
Project-URL: Bug Tracker, https://github.com/Yousif-Abuzeid/nnunetv2-CAM/issues
Keywords: deep learning,medical image segmentation,CAM,explainability,nnUNet
Classifier: Development Status :: 3 - Alpha
Classifier: Intended Audience :: Science/Research
Classifier: License :: OSI Approved :: Apache Software License
Classifier: Programming Language :: Python :: 3
Classifier: Programming Language :: Python :: 3.9
Classifier: Programming Language :: Python :: 3.10
Classifier: Programming Language :: Python :: 3.11
Classifier: Topic :: Scientific/Engineering :: Artificial Intelligence
Classifier: Topic :: Scientific/Engineering :: Medical Science Apps.
Requires-Python: >=3.9
License-File: LICENSE
Requires-Dist: torch>=2.0.0
Requires-Dist: numpy>=1.22.0
Requires-Dist: opencv-python>=4.5.0
Requires-Dist: Pillow>=9.0.0
Requires-Dist: tqdm>=4.60.0
Requires-Dist: SimpleITK>=2.1.0
Requires-Dist: nnunetv2>=2.0
Requires-Dist: grad-cam>=1.4.0
Requires-Dist: acvl-utils>=0.2
Requires-Dist: batchgenerators>=0.25
Provides-Extra: dev
Requires-Dist: pytest>=7.0.0; extra == "dev"
Requires-Dist: pytest-cov>=3.0.0; extra == "dev"
Requires-Dist: black>=22.0.0; extra == "dev"
Requires-Dist: flake8>=4.0.0; extra == "dev"
Requires-Dist: mypy>=0.950; extra == "dev"
Dynamic: license-file
